Topsis_Aashutosh_102053043/Aashutosh_102053043.py
Topsis_Aashutosh_102053043-0.5.dist-info/METADATA
Topsis_Aashutosh_102053043-0.5.dist-info/WHEEL
Topsis_Aashutosh_102053043-0.5.dist-info/entry_points.txt
Topsis_Aashutosh_102053043-0.5.dist-info/top_level.txt
Topsis_Aashutosh_102053043-0.5.dist-info/RECORD
