Metadata-Version: 2.1
Name: Topsis-Aashutosh-102053043
Version: 0.5
Summary: This is a topsis package of version 0.5
Author: Aashutosh Dubey
Author-email: asaashutoshdubey0@gmail.com
License: UNKNOWN
Platform: UNKNOWN
Requires-Dist: pandas
